generalfile/__init__.py
generalfile/configfile.py
generalfile/decorators.py
generalfile/errors.py
generalfile/path.py
generalfile/optional_dependencies/_extension.py
generalfile/optional_dependencies/path_cfg.py
generalfile/optional_dependencies/path_pickle.py
generalfile/optional_dependencies/path_spreadsheet.py
generalfile/optional_dependencies/path_text.py
generalfile/path_bases/__init__.py
generalfile/path_bases/path_diagram.py
generalfile/path_bases/path_envs.py
generalfile/path_bases/path_lock.py
generalfile/path_bases/path_operations.py
generalfile/path_bases/path_scrub.py
generalfile/path_bases/path_strings.py
generalfile/test/setup_workdir.py
generalfile/test/test_cfg.py
generalfile/test/test_configfile.py
generalfile/test/test_generalfile.py
generalfile/test/test_path.py
generalfile/test/test_pickle.py
generalfile/test/test_spreadsheet.py
generalfile/test/test_text.py
generalfile-2.5.17.dist-info/LICENSE
generalfile-2.5.17.dist-info/METADATA
generalfile-2.5.17.dist-info/WHEEL
generalfile-2.5.17.dist-info/top_level.txt
generalfile-2.5.17.dist-info/RECORD
