Metadata-Version: 2.1
Name: generalfile
Version: 2.5.17
Summary: Easily manage files cross platform.
Home-page: https://github.com/ManderaGeneral/generalfile
Author: Rickard "Mandera" Abraham
Author-email: rickard.abraham@gmail.com
License: apache2
Classifier: Topic :: Desktop Environment :: File Managers
Classifier: Programming Language :: Python :: 3.8
Classifier: Programming Language :: Python :: 3.9
Classifier: Programming Language :: Python :: 3.10
Classifier: Programming Language :: Python :: 3.11
Classifier: Programming Language :: Python :: 3.12
Classifier: License :: OSI Approved :: Apache Software License
Classifier: Operating System :: Microsoft :: Windows
Classifier: Operating System :: POSIX :: Linux
License-File: LICENSE
Requires-Dist: generalimport
Requires-Dist: generallibrary
Requires-Dist: send2trash
Requires-Dist: appdirs
Requires-Dist: dill
Provides-Extra: full
Requires-Dist: pandas ; extra == 'full'
Provides-Extra: spreadsheet
Requires-Dist: pandas ; extra == 'spreadsheet'
